[
    {
        "id": 1,
        "name": "Personal Portfolio React SPA",
        "description": "Web App where I show my projects and myself, this version was made with React",
        "image": "https://raw.githubusercontent.com/necogamy/portfolio-react/main/screenshot.png",
        "tags": ["React", "HTML", "CSS", "JavaScript", "QA Testing", "Featured"],
        "demo": "https://nicogamy-portfolio-react-web-app.netlify.app/",
        "github": "https://github.com/necogamy/portfolio-react"
    },
    {
        "id": 2,
        "name": "Personal Portfolio without frameworks",
        "description": "Web App where I show my projects and myself, this version was made without frameworks",
        "image": "https://raw.githubusercontent.com/necogamy/personal-portfolio-website/main/screenshot.png",
        "tags": ["HTML", "CSS", "JavaScript"],
        "demo": "https://necogamy.github.io/personal-portfolio-website/",
        "github": "https://github.com/necogamy/personal-portfolio-website"
    },
    {
        "id": 3,
        "name": "Full Stack PERN Personal Budget Management Web App",
        "description": "A Personal Budget Management web app made with PERN stack, that uses Json Web Token for login and register",
        "image": "https://raw.githubusercontent.com/necogamy/alkemy-fullstack-challenge/main/screenshot.png",
        "tags": ["PostgreSQL", "Express","React", "Node", "Featured", "JavaScript", "SQL", "QA Testing", "HTML", "CSS", "Web Design"],
        "demo": "https://alkemy-fullstack-challenge.herokuapp.com/",
        "github": "https://github.com/necogamy/alkemy-fullstack-challenge"
    },
    {
        "id": 4,
        "name": "Operative System Full Stack Web App",
        "description": "An operative system but web version, made with Node and React",
        "image": "https://raw.githubusercontent.com/necogamy/operative-system-react-node/main/screenshot.png",
        "tags": ["React", "Node", "Featured", "JavaScript", "QA Testing", "HTML", "CSS", "Web Design"],
        "demo": "https://necogamy.github.io/indevelopment",
        "github": "https://github.com/necogamy/operative-system-react-node"
    },
    {
        "id": 5,
        "name": "E-commerce Restful API Microservice",
        "description": "The back-end of an e-commerce made with PostgreSQL and Express",
        "image": "https://www.pqi.com.do/wp-content/uploads/2013/11/dummy-image-square.jpg",
        "tags": ["PostgreSQL", "SQL", "Node", "Express", "Supertest", "QA Testing", "Featured"],
        "demo": "https://github.com/necogamy/ecommerce-app-rest-api",
        "github": "https://github.com/necogamy/ecommerce-app-rest-api"
    },
    {
        "id": 6,
        "name": "Restaurant Database with schema",
        "description": "A database where I show using, one-to-one, many-to-many and one-to-many relations and core concepts of SQL",
        "image": "https://www.pqi.com.do/wp-content/uploads/2013/11/dummy-image-square.jpg",
        "tags": ["PostgreSQL", "SQL"],
        "github": "https://github.com/necogamy/restaurant_database_with_schema"
    },
    {
        "id": 7,
        "name": "Reddit Minimal React & Redux App",
        "description": "A Single Page Application made with React and Redux for state management, while fetching from the JSON API of Reddit, with loading components and other stuff",
        "image": "https://raw.githubusercontent.com/necogamy/reddit-minimal-react-redux-app/main/screenshot.png",
        "tags": ["React", "Redux", "JavaScript", "QA Testing", "HTML", "CSS", "Featured"],
        "demo": "https://reddit-minimal-react-redux.netlify.app/",
        "github": "https://github.com/necogamy/reddit-minimal-react-redux-app"
    },
    {
        "id": 8,
        "name": "JavaScript programs and algorithms",
        "description": "A bundle of javascript programs and algorithms made by me (+32)",
        "image": "https://www.pqi.com.do/wp-content/uploads/2013/11/dummy-image-square.jpg",
        "tags": ["JavaScript", "Algorithms", "Node", "Programs"],
        "github": "https://github.com/necogamy/javascript_programs_and_algorithms"
    },
    {
        "id": 9,
        "name": "Boys programs fetch scripts",
        "description": "Two programs, badboy.js and fetcherboy.js, made for requesting API data and exclusive use with node",
        "image": "https://raw.githubusercontent.com/necogamy/boys-scripts-programs-node/main/screenshot.png",
        "tags": ["JavaScript", "Node", "Programs", "Axios"],
        "github": "https://github.com/necogamy/boys-scripts-programs-node"
    },
    {
        "id": 10,
        "name": "ToDo React App - Single Page Application",
        "description": "A simple Single Page Application, todo list, made with React",
        "image": "https://raw.githubusercontent.com/necogamy/todo-react-app/main/screenshot.png",
        "tags": ["React", "JavaScript", "HTML", "CSS"],
        "demo": "https://nicogamy-todo-react-app.netlify.app/",
        "github": "https://github.com/necogamy/todo-react-app"
    },
    {
        "id": 11,
        "name": "Test Driven Development Example with Mocha and Chai",
        "description": "An example of QA Testing and Test Driven Development with Mocha and Chai",
        "image": "https://www.pqi.com.do/wp-content/uploads/2013/11/dummy-image-square.jpg",
        "tags": ["Mocha", "Chai", "JavaScript", "QA Testing"],
        "github": "https://github.com/necogamy/TDD_with_mocha"
    },
    {
        "id": 12,
        "name": "Appointment Planner React App",
        "description": "a Single Page Application for manage contacts and appointments made with React",
        "image": "https://raw.githubusercontent.com/necogamy/appointment-planner-react-app/main/screenshot.png",
        "tags": ["React", "JavaScript", "CSS", "HTML"],
        "demo": "https://appointment-planner-react-app.netlify.app/",
        "github": "https://github.com/necogamy/appointment-planner-react-app"
    },
    {
        "id": 13,
        "name": "Adopt a pet! Pets React Web App",
        "description": "Pets Web App made with React + React Router Advanced",
        "image": "https://raw.githubusercontent.com/necogamy/web-app-pets-react-router/main/screenshot.png",
        "tags": ["React", "JavaScript", "CSS", "HTML"],
        "demo": "https://pets-web-app-react-router.netlify.app/",
        "github": "https://github.com/necogamy/web-app-pets-react-router"
    },
    {
        "id": 14,
        "name": "Copy Cat React Project",
        "description": "A simple React App where I show advanced concepts of React framework",
        "image": "https://raw.githubusercontent.com/necogamy/copy-cat-react-probe/main/screenshot.png",
        "tags": ["React", "JavaScript", "CSS", "HTML"],
        "demo": "https://copy-cat-react-project.netlify.app/",
        "github": "https://github.com/necogamy/copy-cat-react-probe"
    },
    {
        "id": 15,
        "name": "Test Driven Development in a React App",
        "description": "Example of Test Driven Development with Jest and Enzyme in a React App using RGR principle",
        "image": "https://www.pqi.com.do/wp-content/uploads/2013/11/dummy-image-square.jpg",
        "tags": ["React", "Jest", "Enzyme", "JavaScript", "QA Testing"],
        "github": "https://github.com/necogamy/TDD-react-jest-enzyme"
    },
    {
        "id": 16,
        "name": "Basic Weather App",
        "description": "Weather App without frameworks showing local weather with an API and AJAX using geolocation",
        "image": "https://raw.githubusercontent.com/necogamy/local_weather_API_ajax/main/screenshot.png",
        "tags": ["JavaScript", "AJAX", "HTML", "CSS", "Responsive"],
        "demo": "https://necogamy.github.io/local_weather_API_ajax/",
        "github": "https://github.com/necogamy/local_weather_API_ajax"
    },
    {
        "id": 17,
        "name": "Salomon Outfits Website",
        "description": "A project where I show Grid and Flexbox modern tools of CSS to make a design of a website",
        "image": "https://raw.githubusercontent.com/necogamy/salomon-grid-flexbox-website/main/screenshot.jpeg",
        "tags": ["HTML", "CSS", "Grid", "Flexbox", "Web Design"],
        "demo": "https://necogamy.github.io/salomon-grid-flexbox-website/",
        "github": "https://github.com/necogamy/salomon-grid-flexbox-website"
    },
    {
        "id": 18,
        "name": "Makanawe Cycling Club",
        "description": "Responsive Club Website",
        "image": "https://raw.githubusercontent.com/necogamy/responsive-club-page/main/screenshot.jpeg",
        "tags": ["HTML", "CSS", "Web Design", "Responsive"],
        "demo": "https://necogamy.github.io/responsive-club-page/",
        "github": "https://github.com/necogamy/responsive-club-page"
    },
    {
        "id": 19,
        "name": "Fotomatic Website",
        "description": "A broken website was provided to me and I had to fix it exactly how was expected, I follow a design spec and I had to make it fully responsive",
        "image": "https://raw.githubusercontent.com/necogamy/fotomatic-responsive-website/main/fixed-site.png",
        "tags": ["HTML", "CSS", "Flexbox", "Web Design", "Responsive"],
        "demo": "https://necogamy.github.io/fotomatic-responsive-website/",
        "github": "https://github.com/necogamy/fotomatic-responsive-website"
    },
    {
        "id": 20,
        "name": "Tea Cozy Shop Webpage",
        "description": "Layout based in Flexbox CSS3, following a Design Spec",
        "image": "https://raw.githubusercontent.com/necogamy/tea-shop-webpage-flexbox/main/tea-cozy-redline.jpg",
        "tags": ["HTML", "CSS", "Flexbox", "Web Design"],
        "demo": "https://necogamy.github.io/tea-shop-webpage-flexbox/",
        "github": "https://github.com/necogamy/tea-shop-webpage-flexbox"
    },
    {
        "id": 21,
        "name": "Static Website about countries w/ Bootstrap",
        "description": "Static Web Site 100% maked with Bootstrap, and 100% responsive",
        "image": "https://raw.githubusercontent.com/necogamy/bootstrap-static-website/main/screenshot.png",
        "tags": ["HTML", "Bootstrap", "Flexbox", "Web Design"],
        "demo": "https://necogamy.github.io/bootstrap-static-website/",
        "github": "https://github.com/necogamy/bootstrap-static-website"
    },
    {
        "id": 22,
        "name": "Excursion Website advertises app",
        "description": "Discover hidden places in the world around you",
        "image": "https://raw.githubusercontent.com/necogamy/excursion-advertise-web-app/main/excursion.webp",
        "tags": ["HTML", "CSS", "Web Design"],
        "demo": "https://necogamy.github.io/excursion-advertise-web-app/",
        "github": "https://github.com/necogamy/excursion-advertise-web-app"
    },
    {
        "id": 23,
        "name": "Message Generator Program",
        "description": "A message generator program where I use Sass instead of CSS and It's responsive using Flexbox",
        "image": "https://raw.githubusercontent.com/necogamy/message_generator_program/main/overview.png",
        "tags": ["HTML", "Sass", "JavaScript", "Featured"],
        "demo": "https://necogamy.github.io/message_generator_program/",
        "github": "https://github.com/necogamy/message_generator_program"
    },
    {
        "id": 24,
        "name": "Image Viewer with slide function",
        "description": "A cute image viewer made with jQuery",
        "image": "https://raw.githubusercontent.com/necogamy/image_viewer/main/overview.png",
        "tags": ["HTML", "CSS", "jQuery"],
        "demo": "https://necogamy.github.io/image_viewer/",
        "github": "https://github.com/necogamy/image_viewer"
    },
    {
        "id": 25,
        "name": "Personal Website Webpage",
        "description": "A webpage where I show myself, was my first personal website and I learned a lot of CSS and HTML with this project",
        "image": "https://raw.githubusercontent.com/necogamy/Personal-Portfolio-Webpage/main/media/page.png",
        "tags": ["HTML", "CSS"],
        "demo": "https://necogamy.github.io/Personal-Portfolio-Webpage/",
        "github": "https://github.com/necogamy/Personal-Portfolio-Webpage"
    },
    {
        "id": 26,
        "name": "Number Guesser Script",
        "description": "They provided me with a number-guesser game, and I had to make the logic script",
        "image": "https://www.pqi.com.do/wp-content/uploads/2013/11/dummy-image-square.jpg",
        "tags": ["JavaScript"],
        "github": "https://github.com/necogamy/number-guesser-script"
    },
    {
        "id": 27,
        "name": "Technical Documentation Page",
        "description": "A Responsive Technical Documentation Single Page made with HTML and CSS, about the best kali linux tools",
        "image": "https://raw.githubusercontent.com/necogamy/technicalDocumentationPage/main/screenshot.png",
        "tags": ["HTML", "CSS", "Web Design"],
        "demo": "https://necogamy.github.io/technicalDocumentationPage/",
        "github": "https://github.com/necogamy/technicalDocumentationPage"
    },
    {
        "id": 28,
        "name": "Product Landing Page",
        "description": "A kali linux basic product landing page",
        "image": "https://raw.githubusercontent.com/necogamy/productLandingPage/main/screenshot.png",
        "tags": ["HTML", "CSS", "Web Design"],
        "demo": "https://necogamy.github.io/productLandingPage/",
        "github": "https://github.com/necogamy/productLandingPage"
    },
    {
        "id": 29,
        "name": "Tribute Page",
        "description": "A basic tribute page to Bobby Fisher with HTML & CSS",
        "image": "https://raw.githubusercontent.com/necogamy/basicTributePage/main/screenshot.png",
        "tags": ["HTML", "CSS", "Web Design"],
        "demo": "https://necogamy.github.io/basicTributePage/",
        "github": "https://github.com/necogamy/basicTributePage"
    },
    {
        "id": 30,
        "name": "Survey Form",
        "description": "A basic survey form made with HTML and CSS",
        "image": "https://raw.githubusercontent.com/necogamy/surveyForm/main/screenshot.png",
        "tags": ["HTML", "CSS", "Web Design"],
        "demo": "https://necogamy.github.io/surveyForm/",
        "github": "https://github.com/necogamy/surveyForm"
    },
    {
        "id": 31,
        "name": "Google Homepage Clone",
        "description": "A project that It's a clone of the Google HomePage",
        "image": "https://raw.githubusercontent.com/necogamy/google-homepage/main/screenshot.png",
        "tags": ["HTML", "CSS", "Web Design", "Bootstrap"],
        "demo": "https://necogamy.github.io/google-homepage/",
        "github": "https://github.com/necogamy/google-homepage"
    },
    {
        "id": 32,
        "name": "Daksa Video Webpage",
        "description": "A Web based in a video for a business",
        "image": "https://raw.githubusercontent.com/necogamy/DaksaVideoWebpage/main/screenshot.png",
        "tags": ["HTML", "CSS", "JavaScript", "Web Design"],
        "demo": "https://necogamy.github.io/DaksaVideoWebpage/",
        "github": "https://github.com/necogamy/DaksaVideoWebpage"
    },
    {
        "id": 33,
        "name": "Cybersecure Hackers",
        "description": "A webpage that I made for a homework in my school",
        "image": "https://raw.githubusercontent.com/necogamy/CyberSecureHackers/main/screenshot.png",
        "tags": ["HTML", "CSS", "Web Design"],
        "demo": "https://necogamy.github.io/CyberSecureHackers/",
        "github": "https://github.com/necogamy/CyberSecureHackers"
    }
]
